MANIFEST.in
README.md
pyproject.toml
requirements.txt
setup.cfg
setup.py
source/VERSION
source/__init__.py
source/__main__.py
source/gui.py
source/header.py
source/parser.py
source/assets/default.css
source/assets/fonts.css
source/assets/layout.css
source/assets/magnific-popup.css
source/assets/media-queries.css
source/assets/font-awesome/css/font-awesome.css
source/assets/font-awesome/css/font-awesome.min.css
source/assets/font-awesome/fonts/FontAwesome.otf
source/assets/font-awesome/fonts/fontawesome-webfont.eot
source/assets/font-awesome/fonts/fontawesome-webfont.svg
source/assets/font-awesome/fonts/fontawesome-webfont.ttf
source/assets/font-awesome/fonts/fontawesome-webfont.woff
source/assets/font-awesome/less/bordered-pulled.less
source/assets/font-awesome/less/core.less
source/assets/font-awesome/less/fixed-width.less
source/assets/font-awesome/less/font-awesome.less
source/assets/font-awesome/less/icons.less
source/assets/font-awesome/less/larger.less
source/assets/font-awesome/less/list.less
source/assets/font-awesome/less/mixins.less
source/assets/font-awesome/less/path.less
source/assets/font-awesome/less/rotated-flipped.less
source/assets/font-awesome/less/spinning.less
source/assets/font-awesome/less/stacked.less
source/assets/font-awesome/less/variables.less
source/assets/font-awesome/scss/_bordered-pulled.scss
source/assets/font-awesome/scss/_core.scss
source/assets/font-awesome/scss/_fixed-width.scss
source/assets/font-awesome/scss/_icons.scss
source/assets/font-awesome/scss/_larger.scss
source/assets/font-awesome/scss/_list.scss
source/assets/font-awesome/scss/_mixins.scss
source/assets/font-awesome/scss/_path.scss
source/assets/font-awesome/scss/_rotated-flipped.scss
source/assets/font-awesome/scss/_spinning.scss
source/assets/font-awesome/scss/_stacked.scss
source/assets/font-awesome/scss/_variables.scss
source/assets/font-awesome/scss/font-awesome.scss
source/assets/fontello/css/animation.css
source/assets/fontello/css/fontello-codes.css
